renderlab/__init__.py
renderlab/render_frame.py
renderlab-0.1.20230421184216.dist-info/LICENSE
renderlab-0.1.20230421184216.dist-info/METADATA
renderlab-0.1.20230421184216.dist-info/WHEEL
renderlab-0.1.20230421184216.dist-info/top_level.txt
renderlab-0.1.20230421184216.dist-info/RECORD
