Metadata-Version: 2.1
Name: renderlab
Version: 0.1.20230421184216
Summary: Render Gymnasium environments in Google Colaboratory
Home-page: https://github.com/ryanrudes/renderlab
Author: Ryan Rudes
Author-email: ryanrudes@gmail.com
License: MIT
Keywords: colab,gym,gymnasium,render,openai,rl
Classifier: Development Status :: 5 - Production/Stable
Classifier: Intended Audience :: Developers
Classifier: Intended Audience :: Science/Research
Classifier: Topic :: Scientific/Engineering :: Artificial Intelligence
Classifier: Topic :: Software Development :: Libraries :: Python Modules
Classifier: License :: OSI Approved :: MIT License
Classifier: Programming Language :: Python :: 3.9
License-File: LICENSE
Requires-Dist: moviepy
Requires-Dist: gymnasium
